jbxapi.py
jbxapi-3.24.0.dist-info/entry_points.txt
jbxapi-3.24.0.dist-info/licenses/LICENSE
jbxapi-3.24.0.dist-info/WHEEL
jbxapi-3.24.0.dist-info/METADATA
jbxapi-3.24.0.dist-info/RECORD
