Metadata-Version: 2.4
Name: jbxapi
Version: 3.24.0
Summary: API for Joe Sandbox
Keywords: security,malware,sandbox,sandboxing,joe
Author: Joe Security LLC
Requires-Python: >=2.7, !=3.0, !=3.1.*, !=3.2.*, !=3.3.*, !=3.4.*
Classifier: Development Status :: 5 - Production/Stable
Classifier: Intended Audience :: Developers
Classifier: Topic :: Security
Classifier: License :: OSI Approved :: MIT License
Classifier: Programming Language :: Python :: 2
Classifier: Programming Language :: Python :: 2.7
Classifier: Programming Language :: Python :: 3
License-File: LICENSE
Requires-Dist: requests >=2.18.4,<3
Requires-Dist: pyzipper >=0.3.1; python_version >="3.5"
Project-URL: Homepage, https://github.com/joesecurity/jbxapi
